mrc_insar_common/__init__.py
mrc_insar_common/data/__init__.py
mrc_insar_common/data/data_reader.py
mrc_insar_common/model/__init__.py
mrc_insar_common/model/dncnn/__init__.py
mrc_insar_common/model/dncnn/dncnn.py
mrc_insar_common/model/unet/__init__.py
mrc_insar_common/model/unet/unet_model.py
mrc_insar_common/util/__init__.py
mrc_insar_common/util/sim.py
mrc_insar_common/util/utils.py
mrc_insar_common/util/pt/__init__.py
mrc_insar_common/util/pt/init.py
MRC_InSAR_Common-0.1.2.dist-info/LICENSE
MRC_InSAR_Common-0.1.2.dist-info/METADATA
MRC_InSAR_Common-0.1.2.dist-info/WHEEL
MRC_InSAR_Common-0.1.2.dist-info/top_level.txt
MRC_InSAR_Common-0.1.2.dist-info/RECORD
