Metadata-Version: 2.1
Name: MRC-InSAR-Common
Version: 0.1.2
Summary: UNKNOWN
Home-page: UNKNOWN
Author: Xinyao(Alvin) Sun
Author-email: xinyao1@ualberta.ca
License: UNKNOWN
Platform: UNKNOWN
Requires-Dist: numpy
